asm_cli/__init__.py
asm_cli/asm.py
asm_cli/clparser.py
asm_cli-0.0.26.data/data/README/README.md
asm_cli-0.0.26.dist-info/DESCRIPTION.rst
asm_cli-0.0.26.dist-info/METADATA
asm_cli-0.0.26.dist-info/RECORD
asm_cli-0.0.26.dist-info/WHEEL
asm_cli-0.0.26.dist-info/metadata.json
asm_cli-0.0.26.dist-info/top_level.txt
